{
  "project_info": {
    "project_number": "540348568025",
    "project_id": "sdd-project-2999d",
    "storage_bucket": "sdd-project-2999d.firebasestorage.app"
  },
  "client": [
    {
      "client_info": {
        "mobilesdk_app_id": "1:540348568025:android:5da1caf9b58dc79a3209c8",
        "android_client_info": {
          "package_name": "com.example.smp"
        }
      },
      "oauth_client": [],
      "api_key": [
        {
          "current_key": "AIzaSyBVJC-ruQF1dTk6qFshougv5Dd619uE4-Y"
        }
      ],
      "services": {
        "appinvite_service": {
          "other_platform_oauth_client": []
        }
      }
    }
  ],
  "configuration_version": "1"
}